airflow_run/__init__.py
airflow_run/config-template.yaml
airflow_run/decorators.py
airflow_run/run.py
airflow_run/utils.py
airflow_run-0.4.9.dist-info/LICENSE
airflow_run-0.4.9.dist-info/METADATA
airflow_run-0.4.9.dist-info/WHEEL
airflow_run-0.4.9.dist-info/entry_points.txt
airflow_run-0.4.9.dist-info/top_level.txt
airflow_run-0.4.9.dist-info/RECORD
