Metadata-Version: 2.1
Name: airflow-run
Version: 0.4.9
Summary: Simplified Airflow CLI Tool for Lauching CeleryExecutor Deployment
Home-page: https://github.com/paulokuong/airflow-run
Author: Paulo Kuong
Author-email: paulo.kuong@gmail.com
License: MIT
Keywords: Airflow CeleryExecutor distributed portable deployment runner docker kubernetes
Platform: UNKNOWN
Classifier: Development Status :: 3 - Alpha
Classifier: License :: OSI Approved :: MIT License
Classifier: Programming Language :: Python :: 3.4
Requires-Dist: docker (==4.3.1)
Requires-Dist: pyyaml (==5.3.1)
Requires-Dist: sqlalchemy (>=1.3.13)
Requires-Dist: pika (==1.1.0)
Requires-Dist: psycopg2-binary (==2.8.5)
Requires-Dist: cryptography (==3.2)
